baleotp/Client.py
baleotp/__init__.py
baleotp/version.py
baleotp-0.1.0.dist-info/licenses/LICENSE
baleotp-0.1.0.dist-info/METADATA
baleotp-0.1.0.dist-info/WHEEL
baleotp-0.1.0.dist-info/top_level.txt
baleotp-0.1.0.dist-info/RECORD
