Metadata-Version: 2.4
Name: baleotp
Version: 0.1.0
Summary: Async client for sending OTPs via Bale API
Home-page: https://github.com/Ali-Nabi-Pour/baleotp
Author: Ali NabiPour
Author-email: Ali NabiPour <noyan.joun.89@gmail.com>
License: MIT
Project-URL: Homepage, https://github.com/Ali-Nabi-Pour/baleotp
Classifier: Programming Language :: Python :: 3
Classifier: License :: OSI Approved :: MIT License
Classifier: Operating System :: OS Independent
Requires-Python: >=3.7
License-File: LICENSE
Requires-Dist: aiohttp>=3.8.0
Dynamic: author
Dynamic: home-page
Dynamic: license-file
Dynamic: requires-python
